Workbook

Sheet Planilha1
A1: Data | B1: Débito | C1: Crédito | D1: Valor | F1: Histórico
A2: 01/04/2026 | B2: 1025 | C2: 9 | D2: -1.89 | F2: TAR/CUSTAS COBRANCA
A3: 01/04/2026 | B3: 1004 | C3: 9 | D3: -1648.58 | F3: BOLETO PAGO MENEGOTTI MA
A4: 01/04/2026 | B4: 1004 | C4: 9 | D4: -2747.61 | F4: BOLETO PAGO TRAPP FUNDO
A5: 01/04/2026 | B5: 1004 | C5: 9 | D5: -685.4 | F5: BOLETO PAGO MENEGOTTI MA
A6: 01/04/2026 | B6: 1004 | C6: 9 | D6: -395.27 | F6: BOLETO PAGO MENEGOTTI MA
A7: 01/04/2026 | B7: 1004 | C7: 9 | D7: -837.27 | F7: BOLETO PAGO NOVA CASA DI
A8: 01/04/2026 | B8: 1004 | C8: 9 | D8: -418.63 | F8: BOLETO PAGO CSM-COMPONEN
A9: 01/04/2026 | B9: 1004 | C9: 9 | D9: -514.44 | F9: BOLETO PAGO NOVA DIST DE
A10: 01/04/2026 | B10: 1004 | C10: 9 | D10: -4585.14 | F10: BOLETO PAGO BLACK E DECK
A11: 01/04/2026 | B11: 1004 | C11: 9 | D11: -1300.99 | F11: BOLETO PAGO ROBERT BOSCH
A12: 01/04/2026 | B12: 1004 | C12: 9 | D12: -191.72 | F12: BOLETO PAGO BLACK E DECK
A13: 01/04/2026 | B13: 1004 | C13: 9 | D13: -1132.32 | F13: BOLETO PAGO O V D IMP E
... A15: 01/04/2026 | B15: 1004 | C15: 9 | D15: -150 | F15: BOLETO PAGO SKYTEF
A16: 01/04/2026 | D16: 555 | F16: BOLETO RECEBIDO 01/04S
A17: 01/04/2026 | D17: 12069.39 | F17: RES APLIC AUT MAIS
A18: 01/04/2026 | D18: 207.73 | F18: RECEBIMENTO REDE MAST DB0096006021
A19: 01/04/2026 | D19: 347.28 | F19: RECEBIMENTO REDE VISA DB0096006021
A20: 01/04/2026 | D20: 0.02 | F20: RENDIMENTOS REND PAGO APLIC AUT MAIS
A21: 01/04/2026 | D21: 499.9 | F21: PIX QR CODE RECEBIDO RODRIGO COR01/04
A22: 01/04/2026 | D22: 1499.9 | F22: PIX QR CODE RECEBIDO USINOX ARTI01/04
A23: 01/04/2026 | D23: 96.3 | F23: PIX QR CODE RECEBIDO MARCOS ALBE01/04
A24: 01/04/2026 | D24: 365 | F24: PIX QR CODE RECEBIDO MARCOS ALBE01/04
A25: 02/04/2026 | B25: 1025 | C25: 9 | D25: -9.45 | F25: TAR/CUSTAS COBRANCA
A26: 02/04/2026 | D26: -43.32 | F26: TAR PIXQR LIQ MAQUININHA
A27: 02/04/2026 | D27: -290.9 | F27: TAR PIX QR CODE LIQUIDA
A28: 02/04/2026 | B28: 1004 | C28: 9 | D28: -528.63 | F28: BOLETO PAGO MENEGOTTI MA
A29: 02/04/2026 | B29: 1004 | C29: 9 | D29: -1212.2 | F29: BOLETO PAGO O V D IMP E
A30: 02/04/2026 | D30: -46.76 | F30: BOLETO PAGO MAKITA BR FE
A31: 02/04/2026 | D31: -1707.85 | F31: BOLETO PAGO LYNUS IND CO
A32: 02/04/2026 | D32: -3800 | F32: BOLETO PAGO EXITO CONTAB
A33: 02/04/2026 | D33: -3131.2 | F33: BOLETO PAGO FERRAMENTAS
A34: 02/04/2026 | B34: 1004 | C34: 9 | D34: -944.39 | F34: BOLETO PAGO BLACK E DECK
A35: 02/04/2026 | B35: 1004 | C35: 9 | D35: -1008.79 | F35: BOLETO PAGO O V D IMP E
A36: 02/04/2026 | D36: -1979.88 | F36: BOLETO PAGO KADESH EQUIP
A37: 02/04/2026 | B37: 1004 | C37: 9 | D37: -652.41 | F37: BOLETO PAGO MENEGOTTI MA
A38: 02/04/2026 | D38: -1464.04 | F38: BOLETO PAGO FERRAMENTAS
A39: 02/04/2026 | B39: 1004 | C39: 9 | D39: -1811.38 | F39: BOLETO PAGO TRAMONTINA P
A40: 02/04/2026 | D40: 1690.7 | F40: RECEBIMENTOS SDB COM DE ALIM L
A41: 02/04/2026 | D41: 2721.35 | F41: BOLETO RECEBIDO 02/04S
A42: 02/04/2026 | D42: 127.68 | F42: RES APLIC AUT MAIS
A43: 02/04/2026 | D43: 443.69 | F43: RECEBIMENTO REDE VISA DB0096006021
A44: 02/04/2026 | D44: 159.28 | F44: PIX QR CODE RECEBIDO JOAO ALISSO02/04
A45: 02/04/2026 | D45: 219.9 | F45: PIX QR CODE RECEBIDO L MENDES SI02/04
A46: 02/04/2026 | D46: 179.8 | F46: PIX QR CODE RECEBIDO NATALHA LEI02/04
A47: 02/04/2026 | D47: 209.8 | F47: PIX QR CODE RECEBIDO ROSEANA DE 02/04
A48: 02/04/2026 | D48: 799 | F48: PIX QR CODE RECEBIDO ABIMAEL DA 02/04
A49: 02/04/2026 | D49: 12080 | F49: PIX RECEBIDO BAIFER 02/04
A50: 06/04/2026 | B50: 1025 | C50: 9 | D50: -9.45 | F50: TAR/CUSTAS COBRANCA
A51: 06/04/2026 | D51: -24670.7 | F51: APL APLIC AUT MAIS
A52: 06/04/2026 | D52: -572 | F52: PIX ENVIADO
A53: 06/04/2026 | B53: 1004 | C53: 9 | D53: -238.85 | F53: BOLETO PAGO BLACK E DECK
A54: 06/04/2026 | D54: -635.47 | F54: BOLETO PAGO TECIDOS E AR
A55: 06/04/2026 | B55: 1004 | C55: 9 | D55: -708.33 | F55: BOLETO PAGO CONDOR ATACA
A56: 06/04/2026 | D56: -2275.69 | F56: BOLETO PAGO MARCON INDUS
A57: 06/04/2026 | B57: 1004 | C57: 9 | D57: -1590.58 | F57: BOLETO PAGO CONDOR ATACA
A58: 06/04/2026 | B58: 1004 | C58: 9 | D58: -1054.29 | F58: BOLETO PAGO O V D IMP E
A59: 06/04/2026 | D59: -1062.6 | F59: BOLETO PAGO GARTHEN IND
A60: 06/04/2026 | D60: -1227 | F60: BOLETO PAGO R. R. SOLU
A61: 06/04/2026 | B61: 1004 | C61: 9 | D61: -655.36 | F61: BOLETO PAGO LOTUS COMERC
A62: 06/04/2026 | D62: -1952.74 | F62: BOLETO PAGO BCO ITAUBBA
A63: 06/04/2026 | B63: 1004 | C63: 9 | D63: -2627.66 | F63: BOLETO PAGO TRAMONTINA P
A64: 06/04/2026 | B64: 1004 | C64: 9 | D64: -3387.47 | F64: BOLETO PAGO POSITEC IMPO
A65: 06/04/2026 | D65: -1081.98 | F65: BOLETO PAGO BEL FIX IMPO
A66: 06/04/2026 | D66: -787 | F66: BOLETO PAGO MIDASEC
A67: 06/04/2026 | D67: -163.47 | F67: BOLETO PAGO SPDF LOGISTI
A68: 06/04/2026 | B68: 1004 | C68: 9 | D68: -808.51 | F68: BOLETO PAGO NOVA CASA DI
A69: 06/04/2026 | D69: -2853.5 | F69: BOLETO PAGO ACTOS COM IM
A70: 06/04/2026 | B70: 1004 | C70: 9 | D70: -270 | F70: BOLETO PAGO CONDOR ATACA
A71: 06/04/2026 | B71: 1004 | C71: 9 | D71: -1006.63 | F71: BOLETO PAGO O V D IMP E
A72: 06/04/2026 | D72: -660 | F72: BOLETO PAGO ASL ESPECIAL
A73: 06/04/2026 | B73: 1004 | C73: 9 | D73: -489.73 | F73: BOLETO PAGO MAKITA BR FE
A74: 06/04/2026 | B74: 1004 | C74: 9 | D74: -1043.79 | F74: BOLETO PAGO O V D IMP E
A75: 06/04/2026 | D75: -133.75 | F75: BOLETO PAGO SPDF LOGISTI
A76: 06/04/2026 | B76: 1004 | C76: 9 | D76: -973.6 | F76: BOLETO PAGO POSITEC IMPO
A77: 06/04/2026 | D77: -670.52 | F77: BOLETO PAGO TAMBASA ATAC
A78: 06/04/2026 | D78: 4378.9 | F78: RECEBIMENTOS PROCISA BR PROJ C
A79: 06/04/2026 | D79: 4360.9 | F79: RECEBIMENTOS PROCISA BR PROJ C
A80: 06/04/2026 | D80: 4245.5 | F80: RECEBIMENTOS PROCISA BR PROJ C
A81: 06/04/2026 | D81: 11257.8 | F81: RECEBIMENTOS PROCISA BR PROJ C
A82: 06/04/2026 | D82: 4284.1 | F82: RECEBIMENTOS PROCISA BR PROJ C
A83: 06/04/2026 | D83: 4248.9 | F83: RECEBIMENTOS PROCISA BR PROJ C
A84: 06/04/2026 | D84: 4434.9 | F84: RECEBIMENTOS PROCISA BR PROJ C
A85: 06/04/2026 | D85: 4239.8 | F85: RECEBIMENTOS PROCISA BR PROJ C
A86: 06/04/2026 | D86: 5911.44 | F86: BOLETO RECEBIDO 06/04S
A87: 06/04/2026 | D87: 249.96 | F87: RECEBIMENTO REDE MAST DB0096006021
A88: 06/04/2026 | D88: 36.18 | F88: RECEBIMENTO REDE VISA DB0096006021
... A93: 06/04/2026 | D93: 5100 | F93: PIX RECEBIDO BAIFER 06/04
A94: 07/04/2026 | B94: 1025 | C94: 9 | D94: -24.57 | F94: TAR/CUSTAS COBRANCA
A95: 07/04/2026 | D95: -2080 | F95: PIX ENVIADO
A96: 07/04/2026 | B96: 1004 | C96: 9 | D96: -213.43 | F96: BOLETO PAGO CONDOR ATACA
A97: 07/04/2026 | D97: -3062.68 | F97: BOLETO PAGO INFINITY
A98: 07/04/2026 | D98: -1624.69 | F98: BOLETO PAGO BRITANIA
A99: 07/04/2026 | B99: 1004 | C99: 9 | D99: -4105.73 | F99: BOLETO PAGO POSITEC IMPO
A100: 07/04/2026 | B100: 1004 | C100: 9 | D100: -1229.52 | F100: BOLETO PAGO O V D IMP E
A101: 07/04/2026 | D101: -114.84 | F101: BOLETO PAGO SPDF LOGISTI
A102: 07/04/2026 | D102: -1350.58 | F102: BOLETO PAGO SEMAR IMPORT
A103: 07/04/2026 | B103: 1004 | C103: 9 | D103: -964.48 | F103: BOLETO PAGO MENEGOTTI MA
A104: 07/04/2026 | D104: 3762.91 | F104: BOLETO RECEBIDO 07/04S
A105: 07/04/2026 | D105: 10874.92 | F105: RES APLIC AUT MAIS
...

Sheet Planilha2
A2: BOLETO PAGO BLACK E DECK | B2: =IFERROR(INDEX(Planilha3!B:B,MATCH("*"&SUBSTITUTE(A2,"BOLETO PAGO ","")&"*",Planilha3!B:B,0)),"") -> BLACK E DECKER DO BRASIL LTDA
A3: BOLETO PAGO ROBERT BOSCH | B3: =IFERROR(INDEX(Planilha3!B:B,MATCH("*"&SUBSTITUTE(A3,"BOLETO PAGO ","")&"*",Planilha3!B:B,0)),"") -> ROBERT BOSCH LIMITADA
A4: BOLETO PAGO O V D IMP E | B4: =IFERROR(INDEX(Planilha3!B:B,MATCH("*"&SUBSTITUTE(A4,"BOLETO PAGO ","")&"*",Planilha3!B:B,0)),"")
A5: BOLETO PAGO SKYTEF | B5: =IFERROR(INDEX(Planilha3!B:B,MATCH("*"&SUBSTITUTE(A5,"BOLETO PAGO ","")&"*",Planilha3!B:B,0)),"")
A6: TAR PIXQR LIQ MAQUININHA | B6: =IFERROR(INDEX(Planilha3!B:B,MATCH("*"&SUBSTITUTE(A6,"BOLETO PAGO ","")&"*",Planilha3!B:B,0)),"")
A7: TAR PIX QR CODE LIQUIDA | B7: =IFERROR(INDEX(Planilha3!B:B,MATCH("*"&SUBSTITUTE(A7,"BOLETO PAGO ","")&"*",Planilha3!B:B,0)),"")
A8: BOLETO PAGO MAKITA BR FE | B8: =IFERROR(INDEX(Planilha3!B:B,MATCH("*"&SUBSTITUTE(A8,"BOLETO PAGO ","")&"*",Planilha3!B:B,0)),"")
A9: BOLETO PAGO LYNUS IND CO | B9: =IFERROR(INDEX(Planilha3!B:B,MATCH("*"&SUBSTITUTE(A9,"BOLETO PAGO ","")&"*",Planilha3!B:B,0)),"")
A10: BOLETO PAGO EXITO CONTAB | B10: =IFERROR(INDEX(Planilha3!B:B,MATCH("*"&SUBSTITUTE(A10,"BOLETO PAGO ","")&"*",Planilha3!B:B,0)),"")
A11: BOLETO PAGO FERRAMENTAS | B11: =IFERROR(INDEX(Planilha3!B:B,MATCH("*"&SUBSTITUTE(A11,"BOLETO PAGO ","")&"*",Planilha3!B:B,0)),"") -> GURGELMIX MAQUINAS E FERRAMENTAS S.A.
A12: BOLETO PAGO KADESH EQUIP | B12: =IFERROR(INDEX(Planilha3!B:B,MATCH("*"&SUBSTITUTE(A12,"BOLETO PAGO ","")&"*",Planilha3!B:B,0)),"")
A13: BOLETO PAGO TRAMONTINA P | B13: =IFERROR(INDEX(Planilha3!B:B,MATCH("*"&SUBSTITUTE(A13,"BOLETO PAGO ","")&"*",Planilha3!B:B,0)),"") -> TRAMONTINA PLANALTO S/A
... A81: BOLETO PAGO VCH IMPORTAD | B81: =IFERROR(INDEX(Planilha3!B:B,MATCH("*"&SUBSTITUTE(A81,"BOLETO PAGO ","")&"*",Planilha3!B:B,0)),"")

Sheet Planilha3
A1: FORNECEDORES | B1: BLACK E DECKER DO BRASIL LTDA
A2: FORNECEDORES | B2: BLACK E DECKER DO BRASIL LTDA
A3: FORNECEDORES | B3: CSM COMPONENTES SISTEMAS E MAQUINAS PARA CONSTRUCA
A4: FORNECEDORES | B4: GURGELMIX MAQUINAS E FERRAMENTAS S.A.
A5: FORNECEDORES | B5: HIDROMEPE ENG. MANUT.HIDR. IND. COM.LTDA
A6: FORNECEDORES | B6: MENEGOTTI INDUSTRIAS METALURGICAS LTDA EM RECUPER.
A7: FORNECEDORES | B7: MENEGOTTI INDUSTRIAS METALURGICAS LTDA EM RECUPER.
A8: FORNECEDORES | B8: MENEGOTTI INDUSTRIAS METALURGICAS LTDA EM RECUPER.
A9: FORNECEDORES | B9: METALURGICA TRAPP LTDA
A10: FORNECEDORES | B10: MULTIVAREJO ES LTDA
A11: FORNECEDORES | B11: NOVA CASA DIST MAT CONST S/A DF FL 02
A12: FORNECEDORES | B12: NOVA DISTRIBUIDORA DE FERRAGENS LTDA
... A343: FORNECEDORES | B343: VCH - IMPORTADORA EXPORTADORA E DISTRIBUICAO DE P
